Metadata-Version: 1.1
Name: fordfulkerson-prueba
Version: 0.0.2
Summary: Implementación del método Fork Fulkerson
Home-page: UNKNOWN
Author: Equipo 2
Author-email: UNKNOWN
License: MIT
Keywords: max flow
Platform: UNKNOWN
Classifier: Development Status :: 5 - Production/Stable
Classifier: Intended Audience :: Education
Classifier: Operating System :: Microsoft :: Windows :: Windows 10
Classifier: License :: OSI Approved :: MIT License
Classifier: Programming Language :: Python :: 3
